CHANGES.txt
CREDITS.txt
MANIFEST.in
README.txt
setup.py
src/hurry/__init__.py
src/hurry.jqplot.egg-info/PKG-INFO
src/hurry.jqplot.egg-info/SOURCES.txt
src/hurry.jqplot.egg-info/dependency_links.txt
src/hurry.jqplot.egg-info/entry_points.txt
src/hurry.jqplot.egg-info/namespace_packages.txt
src/hurry.jqplot.egg-info/not-zip-safe
src/hurry.jqplot.egg-info/requires.txt
src/hurry.jqplot.egg-info/top_level.txt
src/hurry/jqplot/__init__.py
src/hurry/jqplot/_lib.py
src/hurry/jqplot/configure.zcml
src/hurry/jqplot/jqplot.txt
src/hurry/jqplot/prepare.py
src/hurry/jqplot/tests.py
src/hurry/jqplot/jqplot-build/excanvas.js
src/hurry/jqplot/jqplot-build/excanvas.min.js
src/hurry/jqplot/jqplot-build/jquery.jqplot.css
src/hurry/jqplot/jqplot-build/jquery.jqplot.js
src/hurry/jqplot/jqplot-build/jquery.jqplot.min.css
src/hurry/jqplot/jqplot-build/jquery.jqplot.min.js
src/hurry/jqplot/jqplot-build/plugins/jqplot.barRenderer.js
src/hurry/jqplot/jqplot-build/plugins/jqplot.barRenderer.min.js
src/hurry/jqplot/jqplot-build/plugins/jqplot.canvasAxisLabelRenderer.js
src/hurry/jqplot/jqplot-build/plugins/jqplot.canvasAxisLabelRenderer.min.js
src/hurry/jqplot/jqplot-build/plugins/jqplot.canvasAxisTickRenderer.js
src/hurry/jqplot/jqplot-build/plugins/jqplot.canvasAxisTickRenderer.min.js
src/hurry/jqplot/jqplot-build/plugins/jqplot.canvasTextRenderer.js
src/hurry/jqplot/jqplot-build/plugins/jqplot.canvasTextRenderer.min.js
src/hurry/jqplot/jqplot-build/plugins/jqplot.categoryAxisRenderer.js
src/hurry/jqplot/jqplot-build/plugins/jqplot.categoryAxisRenderer.min.js
src/hurry/jqplot/jqplot-build/plugins/jqplot.cursor.js
src/hurry/jqplot/jqplot-build/plugins/jqplot.cursor.min.js
src/hurry/jqplot/jqplot-build/plugins/jqplot.dateAxisRenderer.js
src/hurry/jqplot/jqplot-build/plugins/jqplot.dateAxisRenderer.min.js
src/hurry/jqplot/jqplot-build/plugins/jqplot.dragable.js
src/hurry/jqplot/jqplot-build/plugins/jqplot.dragable.min.js
src/hurry/jqplot/jqplot-build/plugins/jqplot.highlighter.js
src/hurry/jqplot/jqplot-build/plugins/jqplot.highlighter.min.js
src/hurry/jqplot/jqplot-build/plugins/jqplot.logAxisRenderer.js
src/hurry/jqplot/jqplot-build/plugins/jqplot.logAxisRenderer.min.js
src/hurry/jqplot/jqplot-build/plugins/jqplot.mekkoAxisRenderer.js
src/hurry/jqplot/jqplot-build/plugins/jqplot.mekkoAxisRenderer.min.js
