Metadata-Version: 1.0
Name: hurry.jqplot
Version: 0.9.7.1
Summary: hurry.resource style resources for jqPlot.
Home-page: http://github.com/jmichiel/hurry.jqplot
Author: Jeroen Michiel
Author-email: jmichiel@yahoo.com
License: UNKNOWN
Platform: UNKNOWN
